Metadata-Version: 2.1
Name: django-image-collection
Version: 0.3.0
Summary: A reusable Django app to organise images in collections.
